{
  "project_info": {
    "project_number": "410187216810",
    "project_id": "anti-corruption-2104",
    "storage_bucket": "anti-corruption-2104.appspot.com"
  },
  "client": [
    {
      "client_info": {
        "mobilesdk_app_id": "1:410187216810:android:f0d5728e0dabe73cc11dd3",
        "android_client_info": {
          "package_name": "com.japnoor.anticorruption"
        }
      },
      "oauth_client": [
        {
          "client_id": "410187216810-6jg0kfs6rvrt8tj2153kkgevj9btij14.apps.googleusercontent.com",
          "client_type": 3
        }
      ],
      "api_key": [
        {
          "current_key": "AIzaSyAvSlA_-VZVFXDJ5WEh5BcWsVExPWNiG1k"
        }
      ],
      "services": {
        "appinvite_service": {
          "other_platform_oauth_client": [
            {
              "client_id": "410187216810-6jg0kfs6rvrt8tj2153kkgevj9btij14.apps.googleusercontent.com",
              "client_type": 3
            }
          ]
        }
      }
    }
  ],
  "configuration_version": "1"
}